fatoora/__init__.py
fatoora/fatoora.py
fatoora/version.py
fatoora-3.0.3.dist-info/LICENSE
fatoora-3.0.3.dist-info/METADATA
fatoora-3.0.3.dist-info/WHEEL
fatoora-3.0.3.dist-info/top_level.txt
fatoora-3.0.3.dist-info/RECORD
