Metadata-Version: 2.1
Name: fatoora
Version: 3.0.3
Summary: An unofficial package help developers to implement ZATCA (Fatoora) QR code easily which required for e-invoicing
Home-page: https://github.com/TheAwiteb/fatoora
Author: TheAwiteb
Author-email: Awiteb@hotmail.com
License: MIT
Keywords: fatoora,Fatoora,ZATCA,QR-Code
Classifier: Programming Language :: Python :: 3.8
Classifier: Programming Language :: Python :: 3.9
Classifier: Programming Language :: Python :: 3.10
Classifier: License :: OSI Approved :: MIT License
Classifier: Operating System :: OS Independent
Requires-Python: >=3.8
License-File: LICENSE
Requires-Dist: decorator (==5.1.1)
Requires-Dist: numpy (==1.22.0)
Requires-Dist: opencv-python (==4.5.5.64)
Requires-Dist: Pillow (==9.1.1)
Requires-Dist: pydantic (==1.9.0)
Requires-Dist: qrcode (==7.3.1)
Requires-Dist: six (==1.16.0)
Requires-Dist: typing-extensions (==4.1.1)
Requires-Dist: uttlv (==0.6.0)
Requires-Dist: validators (==0.18.2)
